blackref/__init__.py
blackref-0.1.9.dist-info/LICENSE.txt
blackref-0.1.9.dist-info/METADATA
blackref-0.1.9.dist-info/WHEEL
blackref-0.1.9.dist-info/entry_points.txt
blackref-0.1.9.dist-info/top_level.txt
blackref-0.1.9.dist-info/RECORD
