Metadata-Version: 2.1
Name: blackref
Version: 0.1.9
Summary: An uncompromising BibTeX/BibLaTeX reference list formatter.
Home-page: https://github.com/dvolgyes/blackref
Author: David Völgyes
Author-email: david.volgyes@ieee.org
License: AGPLv3
Keywords: code formattig,latex,bibtex,biblatex
Classifier: Development Status :: 4 - Beta
Classifier: Intended Audience :: Developers
Classifier: License :: OSI Approved :: GNU Affero General Public License v3
Classifier: Natural Language :: English
Classifier: Programming Language :: Python :: 3.9
Classifier: Programming Language :: Python :: 3.10
Classifier: Programming Language :: Python :: 3.11
Classifier: Programming Language :: Python :: 3.12
Requires-Python: >=3.9
License-File: LICENSE.txt
Requires-Dist: bibtexparser
Requires-Dist: configargparse
Requires-Dist: isbnlib
Requires-Dist: pylatexenc
